README.rst
gitr.py
poppage
poppage.bat
poppage.py
setup.py
utilconf.py
poppage.egg-info/PKG-INFO
poppage.egg-info/SOURCES.txt
poppage.egg-info/dependency_links.txt
poppage.egg-info/requires.txt
poppage.egg-info/top_level.txt