Metadata-Version: 1.1
Name: poppage
Version: 0.8.1
Summary: Utility for generating files and directories from templates.
Home-page: https://github.com/jeffrimko/PopPage
Author: Jeff Rimko
Author-email: jeffrimko@gmail.com
License: MIT
Keywords: project-templates file-templates file-generation
Platform: UNKNOWN
Classifier: Development Status :: 4 - Beta
Classifier: Topic :: Utilities
Classifier: Programming Language :: Python :: 2.7
Classifier: Programming Language :: Python :: 3
